<?xml version="1.0" encoding="UTF-8"?>
<con:soapui-project id="c10ac4da-209c-4ea7-9bd0-d2055712e00b" created="3.61.0" activeEnvironment="Default environment" encryptionMode="Not encrypted" name="PetStoreRest" projectVersion="" updated="3.61.0 2025-06-17T10:42:49Z" xmlns:con="http://eviware.com/soapui/config">
  <con:settings/>
  <con:interface xsi:type="con:RestService" id="d9937785-5ea2-4b40-8e03-5755ee9c86fb" wadlVersion="http://wadl.dev.java.net/2009/02" name="https://petstore.swagger.io" type="rest" xmlns:xsi="http://www.w3.org/2001/XMLSchema-instance">
    <con:settings id="20baa16b-fc07-4800-bd48-7d7936667d7b"/>
    <con:definitionCache type="TEXT" rootPart=""/>
    <con:endpoints>
      <con:endpoint>https://petstore.swagger.io</con:endpoint>
    </con:endpoints>
    <con:resource name="Pet" path="/v2/pet" id="ab74e154-195c-414f-b7ea-4995fbd0a14a">
      <con:settings/>
      <con:parameters/>
      <con:method name="Pet" id="95270dae-cd21-4711-a738-f2a5ab428b30" method="POST">
        <con:settings/>
        <con:parameters/>
        <con:representation type="RESPONSE">
          <con:mediaType>application/json</con:mediaType>
          <con:status>200</con:status>
          <con:params/>
          <con:element xmlns:pet="https://petstore.swagger.io/v2/pet">pet:Response</con:element>
        </con:representation>
        <con:representation type="REQUEST">
          <con:mediaType>application/json</con:mediaType>
          <con:params/>
        </con:representation>
        <con:representation type="FAULT">
          <con:mediaType>application/json</con:mediaType>
          <con:status>500</con:status>
          <con:params/>
          <con:element xmlns:pet="https://petstore.swagger.io/v2/pet">pet:Fault</con:element>
        </con:representation>
        <con:request name="Request 1" id="43855870-2860-44c2-9d84-33fcd52848ef" mediaType="application/json">
          <con:settings/>
          <con:endpoint>https://petstore.swagger.io</con:endpoint>
          <con:credentials>
            <con:selectedAuthProfile>No Authorization</con:selectedAuthProfile>
            <con:authType>No Authorization</con:authType>
          </con:credentials>
          <con:parameters/>
        </con:request>
      </con:method>
      <con:method name="Pet 2" id="51fafbec-391d-4f6f-b051-e7fd8fc12a46" method="POST">
        <con:settings/>
        <con:parameters/>
        <con:request name="Request 1" id="94670688-1afa-4c76-8c60-f09102618e4b" mediaType="application/json">
          <con:settings/>
          <con:endpoint>https://petstore.swagger.io</con:endpoint>
          <con:credentials>
            <con:selectedAuthProfile>No Authorization</con:selectedAuthProfile>
            <con:authType>No Authorization</con:authType>
          </con:credentials>
          <con:parameters/>
        </con:request>
      </con:method>
    </con:resource>
    <con:resource name="FindByStatus" path="/v2/pet/findByStatus" id="1688c189-7f6c-4d89-98f4-66c5dd439cce">
      <con:settings/>
      <con:parameters/>
      <con:method name="FindByStatus" id="a8ca75ec-7efc-42ca-8dd5-9fefa70d5bd8" method="GET">
        <con:settings/>
        <con:parameters>
          <con:parameter required="true">
            <con:name>status</con:name>
            <con:value>sold</con:value>
            <con:style>QUERY</con:style>
            <con:default>sold</con:default>
            <con:path xsi:nil="true"/>
            <con:description xsi:nil="true"/>
          </con:parameter>
        </con:parameters>
        <con:representation type="RESPONSE">
          <con:mediaType>application/json</con:mediaType>
          <con:status>200</con:status>
          <con:params/>
          <con:element>Response</con:element>
        </con:representation>
        <con:request name="Request 1" id="42c9062d-c4e7-44d3-b3fa-de7cdee410bb" mediaType="application/json">
          <con:settings/>
          <con:endpoint>https://petstore.swagger.io</con:endpoint>
          <con:credentials>
            <con:selectedAuthProfile>No Authorization</con:selectedAuthProfile>
            <con:authType>No Authorization</con:authType>
          </con:credentials>
          <con:parameters>
            <con:entry key="status" value="sold"/>
          </con:parameters>
          <con:parameterOrder>
            <con:entry>status</con:entry>
          </con:parameterOrder>
        </con:request>
      </con:method>
      <con:method name="FindByStatus 2" id="322bae1f-567d-4fb6-9712-cb60ba78a9e8" method="GET">
        <con:settings/>
        <con:parameters>
          <con:parameter required="true">
            <con:name>status</con:name>
            <con:value>sold</con:value>
            <con:style>QUERY</con:style>
            <con:default>sold</con:default>
            <con:path xsi:nil="true"/>
            <con:description xsi:nil="true"/>
          </con:parameter>
        </con:parameters>
        <con:request name="Request 1" id="c5343e68-9a4b-4df4-b2de-1c311489bf2c" mediaType="application/json">
          <con:settings/>
          <con:endpoint>https://petstore.swagger.io</con:endpoint>
          <con:credentials>
            <con:selectedAuthProfile>No Authorization</con:selectedAuthProfile>
            <con:authType>No Authorization</con:authType>
          </con:credentials>
          <con:parameters>
            <con:entry key="status" value="sold"/>
          </con:parameters>
          <con:parameterOrder>
            <con:entry>status</con:entry>
          </con:parameterOrder>
        </con:request>
      </con:method>
    </con:resource>
    <con:resource name="PetId" path="/v2/pet/{petId}" id="08075b8d-d0d0-4ff7-863d-b5b997fad835">
      <con:settings/>
      <con:parameters/>
      <con:method name="PetId" id="df7f9b0e-605c-43fe-858e-9c2f7197034a" method="DELETE">
        <con:settings/>
        <con:parameters>
          <con:parameter required="true">
            <con:name>petId</con:name>
            <con:value>petId</con:value>
            <con:style>TEMPLATE</con:style>
            <con:default>petId</con:default>
            <con:path xsi:nil="true"/>
            <con:description xsi:nil="true"/>
          </con:parameter>
        </con:parameters>
        <con:representation type="REQUEST">
          <con:mediaType>application/json</con:mediaType>
          <con:params/>
        </con:representation>
        <con:representation type="FAULT">
          <con:mediaType xsi:nil="true"/>
          <con:status>404</con:status>
          <con:params/>
          <con:element>data</con:element>
        </con:representation>
        <con:representation type="RESPONSE">
          <con:mediaType>application/json</con:mediaType>
          <con:status>200</con:status>
          <con:params/>
          <con:element xmlns:ns="https://petstore.swagger.io/v2/pet/77232">ns:Response</con:element>
        </con:representation>
        <con:request name="Request 1" id="d0086ff5-5e06-4bd9-8f9a-d324ddb62d6c" mediaType="application/json">
          <con:settings/>
          <con:endpoint>https://petstore.swagger.io</con:endpoint>
          <con:credentials>
            <con:selectedAuthProfile>No Authorization</con:selectedAuthProfile>
            <con:authType>No Authorization</con:authType>
          </con:credentials>
          <con:parameters>
            <con:entry key="petId" value="petId"/>
          </con:parameters>
          <con:parameterOrder>
            <con:entry>petId</con:entry>
          </con:parameterOrder>
        </con:request>
      </con:method>
      <con:method name="PetId 2" id="576c6e6b-6d46-4c85-86ee-1334c10c8d9c" method="DELETE">
        <con:settings/>
        <con:parameters>
          <con:parameter required="true">
            <con:name>petId</con:name>
            <con:value>petId</con:value>
            <con:style>TEMPLATE</con:style>
            <con:default>petId</con:default>
            <con:path xsi:nil="true"/>
            <con:description xsi:nil="true"/>
          </con:parameter>
        </con:parameters>
        <con:request name="Request 1" id="173f4bde-d171-4360-b859-13c702c266c8" mediaType="application/json">
          <con:settings/>
          <con:endpoint>https://petstore.swagger.io</con:endpoint>
          <con:credentials>
            <con:selectedAuthProfile>No Authorization</con:selectedAuthProfile>
            <con:authType>No Authorization</con:authType>
          </con:credentials>
          <con:parameters>
            <con:entry key="petId" value="petId"/>
          </con:parameters>
          <con:parameterOrder>
            <con:entry>petId</con:entry>
          </con:parameterOrder>
        </con:request>
      </con:method>
    </con:resource>
  </con:interface>
  <con:testSuite id="a605dc1e-16de-4f17-b995-404e5ddbabe7" name="Test Suite">
    <con:settings id="4132cdec-3f3f-48e7-a6f9-e62418bbf010"/>
    <con:runType>SEQUENTIAL</con:runType>
    <con:testCase id="ea76bd64-5ea1-4ed3-b54b-feda1dd9c9cc" discardOkResults="false" failOnError="false" failTestCaseOnErrors="true" keepSession="false" name="Activity1" searchProperties="true" timeout="0">
      <con:settings/>
      <con:testStep type="datasource" name="DataSource" id="2169256e-c705-4913-9a43-486c4bbf487e">
        <con:settings/>
        <con:config xsi:type="con:DataSourceStep" xmlns:xsi="http://www.w3.org/2001/XMLSchema-instance">
          <con:dataSource type="Grid">
            <con:configuration>
              <check><![CDATA[<xml-fragment><con:entry xmlns:con="http://eviware.com/soapui/config">true</con:entry><con:entry xmlns:con="http://eviware.com/soapui/config">true</con:entry><con:entry xmlns:con="http://eviware.com/soapui/config">true</con:entry></xml-fragment>]]></check>
              <row><![CDATA[<xml-fragment><con:entry xmlns:con="http://eviware.com/soapui/config">77232</con:entry><con:entry xmlns:con="http://eviware.com/soapui/config">Riley</con:entry><con:entry xmlns:con="http://eviware.com/soapui/config">alive</con:entry><con:entry xmlns:con="http://eviware.com/soapui/config"/></xml-fragment>]]></row>
              <row><![CDATA[<xml-fragment><con:entry xmlns:con="http://eviware.com/soapui/config">77233</con:entry><con:entry xmlns:con="http://eviware.com/soapui/config">Gretel</con:entry><con:entry xmlns:con="http://eviware.com/soapui/config">alive</con:entry><con:entry xmlns:con="http://eviware.com/soapui/config"/></xml-fragment>]]></row>
              <row><![CDATA[<xml-fragment><con:entry xmlns:con="http://eviware.com/soapui/config">77234</con:entry><con:entry xmlns:con="http://eviware.com/soapui/config">Hansel</con:entry><con:entry xmlns:con="http://eviware.com/soapui/config">alive</con:entry><con:entry xmlns:con="http://eviware.com/soapui/config"/></xml-fragment>]]></row>
              <recognizeAsPlainText>true</recognizeAsPlainText>
            </con:configuration>
          </con:dataSource>
          <con:shared>true</con:shared>
          <con:restartShared>true</con:restartShared>
          <con:property>petId</con:property>
          <con:property>petName</con:property>
          <con:property>petStatus</con:property>
          <con:restartOnRun>true</con:restartOnRun>
          <con:stopDatasourceExhausted>false</con:stopDatasourceExhausted>
        </con:config>
      </con:testStep>
      <con:testStep type="restrequest" name="POST Request" id="9ab2a6eb-8f8f-4e5d-9093-c53673ebb812">
        <con:settings/>
        <con:config service="https://petstore.swagger.io" resourcePath="/v2/pet" methodName="Pet" xsi:type="con:RestRequestStep" xmlns:xsi="http://www.w3.org/2001/XMLSchema-instance">
          <con:restRequest name="POST Request" id="43855870-2860-44c2-9d84-33fcd52848ef" mediaType="application/json" postQueryString="false">
            <con:settings>
              <con:setting id="com.eviware.soapui.impl.wsdl.WsdlRequest@request-headers">&lt;xml-fragment/></con:setting>
            </con:settings>
            <con:endpoint>https://petstore.swagger.io</con:endpoint>
            <con:request>{\r
   "id":${DataSource#petId},\r
   "name":"${DataSource#petName}",\r
   "status":"${DataSource#petStatus}"
}</con:request>
            <con:originalUri>https://petstore.swagger.io/v2/pet</con:originalUri>
            <con:assertion type="Valid HTTP Status Codes" id="1e037a9d-2b64-4b4c-9ccb-8edbe9ca662f" name="Valid HTTP Status Codes">
              <con:settings/>
              <con:configuration>
                <codes>200</codes>
              </con:configuration>
            </con:assertion>
            <con:assertion type="JsonPath Match" id="e6cbfe60-10e5-4cf3-9fe9-b2b21120c7d5" name="JSONPath Match">
              <con:configuration>
                <path>$['name']</path>
                <content>${DataSource#petName}</content>
                <allowWildcards>false</allowWildcards>
                <ignoreNamspaceDifferences>false</ignoreNamspaceDifferences>
                <ignoreComments>false</ignoreComments>
              </con:configuration>
            </con:assertion>
            <con:credentials>
              <con:selectedAuthProfile>No Authorization</con:selectedAuthProfile>
              <con:authType>No Authorization</con:authType>
            </con:credentials>
            <con:jmsConfig JMSDeliveryMode="PERSISTENT"/>
            <con:parameters/>
          </con:restRequest>
        </con:config>
      </con:testStep>
      <con:testStep type="transfer" name="Property Transfer" id="4714457b-d863-4720-8316-cdff75517eae">
        <con:settings/>
        <con:config xsi:type="con:PropertyTransfersStep" xmlns:xsi="http://www.w3.org/2001/XMLSchema-instance">
          <con:transfers setNullOnMissingSource="true" transferTextContent="true" failOnError="true" ignoreEmpty="false" transferToAll="false" entitize="false" transferChildNodes="false">
            <con:name>statusTransfer</con:name>
            <con:sourceType>Response</con:sourceType>
            <con:sourceStep>POST Request</con:sourceStep>
            <con:sourcePath>$['status']</con:sourcePath>
            <con:targetType>status</con:targetType>
            <con:targetStep>GET Request</con:targetStep>
            <con:targetPath/>
            <con:type>JSONPATH</con:type>
            <con:targetTransferType>JSONPATH</con:targetTransferType>
            <con:upgraded>true</con:upgraded>
          </con:transfers>
          <con:transfers setNullOnMissingSource="true" transferTextContent="true" failOnError="true" ignoreEmpty="false" transferToAll="false" entitize="false" transferChildNodes="false">
            <con:name>idTransfer</con:name>
            <con:sourceType>Response</con:sourceType>
            <con:sourceStep>POST Request</con:sourceStep>
            <con:sourcePath>$['id']</con:sourcePath>
            <con:targetType>petId</con:targetType>
            <con:targetStep>DELETE Request</con:targetStep>
            <con:type>JSONPATH</con:type>
            <con:targetTransferType>JSONPATH</con:targetTransferType>
            <con:upgraded>true</con:upgraded>
          </con:transfers>
        </con:config>
      </con:testStep>
      <con:testStep type="restrequest" name="GET Request" id="308116ca-a6b5-46dd-bf3b-c75913794ab0">
        <con:settings/>
        <con:config service="https://petstore.swagger.io" resourcePath="/v2/pet/findByStatus" methodName="FindByStatus" xsi:type="con:RestRequestStep" xmlns:xsi="http://www.w3.org/2001/XMLSchema-instance">
          <con:restRequest name="GET Request" id="42c9062d-c4e7-44d3-b3fa-de7cdee410bb" mediaType="application/json">
            <con:settings>
              <con:setting id="com.eviware.soapui.impl.wsdl.WsdlRequest@request-headers">&lt;xml-fragment/></con:setting>
            </con:settings>
            <con:endpoint>https://petstore.swagger.io</con:endpoint>
            <con:request/>
            <con:originalUri>https://petstore.swagger.io/v2/pet/findByStatus</con:originalUri>
            <con:assertion type="Valid HTTP Status Codes" id="ef97a2f6-551f-4064-99cc-ca49640d3484" name="Valid HTTP Status Codes">
              <con:settings/>
              <con:configuration>
                <codes>200</codes>
              </con:configuration>
            </con:assertion>
            <con:credentials>
              <con:selectedAuthProfile>No Authorization</con:selectedAuthProfile>
              <con:authType>No Authorization</con:authType>
            </con:credentials>
            <con:jmsConfig JMSDeliveryMode="PERSISTENT"/>
            <con:parameters>
              <con:entry key="status" value="alive"/>
            </con:parameters>
            <con:parameterOrder>
              <con:entry>status</con:entry>
            </con:parameterOrder>
          </con:restRequest>
        </con:config>
      </con:testStep>
      <con:testStep type="restrequest" name="DELETE Request" id="3836a961-01fa-4237-9bf2-3592ab98d8bf">
        <con:settings/>
        <con:config service="https://petstore.swagger.io" resourcePath="/v2/pet/{petId}" methodName="PetId" xsi:type="con:RestRequestStep" xmlns:xsi="http://www.w3.org/2001/XMLSchema-instance">
          <con:restRequest name="DELETE Request" id="d0086ff5-5e06-4bd9-8f9a-d324ddb62d6c" mediaType="application/json" postQueryString="false">
            <con:settings>
              <con:setting id="com.eviware.soapui.impl.wsdl.WsdlRequest@request-headers">&lt;xml-fragment/></con:setting>
            </con:settings>
            <con:endpoint>https://petstore.swagger.io</con:endpoint>
            <con:request/>
            <con:originalUri>https://petstore.swagger.io/v2/pet/77232</con:originalUri>
            <con:assertion type="Valid HTTP Status Codes" id="03572c51-d359-45b3-bb5a-e047330cbc4a" name="Valid HTTP Status Codes">
              <con:settings/>
              <con:configuration>
                <codes>200</codes>
              </con:configuration>
            </con:assertion>
            <con:credentials>
              <con:selectedAuthProfile>No Authorization</con:selectedAuthProfile>
              <con:authType>No Authorization</con:authType>
            </con:credentials>
            <con:jmsConfig JMSDeliveryMode="PERSISTENT"/>
            <con:parameters>
              <con:entry key="petId" value="77234"/>
            </con:parameters>
            <con:parameterOrder>
              <con:entry>petId</con:entry>
            </con:parameterOrder>
          </con:restRequest>
        </con:config>
      </con:testStep>
      <con:testStep type="datasourceloop" name="Data Source Loop" id="bc022b69-9d68-433d-bb93-6340db648bf0">
        <con:settings/>
        <con:config>
          <dataSourceStep>DataSource</dataSourceStep>
          <targetStep>POST Request</targetStep>
          <discardResults>true</discardResults>
        </con:config>
      </con:testStep>
      <con:properties/>
      <con:reportParameters/>
      <con:breakPoints>
        <con:testStepId>2169256e-c705-4913-9a43-486c4bbf487e</con:testStepId>
        <con:status>NONE</con:status>
        <con:properties/>
      </con:breakPoints>
      <con:breakPoints>
        <con:testStepId>9ab2a6eb-8f8f-4e5d-9093-c53673ebb812</con:testStepId>
        <con:status>NONE</con:status>
        <con:properties/>
      </con:breakPoints>
      <con:breakPoints>
        <con:testStepId>4714457b-d863-4720-8316-cdff75517eae</con:testStepId>
        <con:status>NONE</con:status>
        <con:properties/>
      </con:breakPoints>
      <con:breakPoints>
        <con:testStepId>308116ca-a6b5-46dd-bf3b-c75913794ab0</con:testStepId>
        <con:status>NONE</con:status>
        <con:properties/>
      </con:breakPoints>
      <con:breakPoints>
        <con:testStepId>3836a961-01fa-4237-9bf2-3592ab98d8bf</con:testStepId>
        <con:status>NONE</con:status>
        <con:properties/>
      </con:breakPoints>
      <con:breakPoints>
        <con:testStepId>bc022b69-9d68-433d-bb93-6340db648bf0</con:testStepId>
        <con:status>NONE</con:status>
        <con:properties/>
      </con:breakPoints>
    </con:testCase>
    <con:testCase id="44416536-c8b1-43ad-847a-f7351484a22b" discardOkResults="false" failOnError="false" failTestCaseOnErrors="true" keepSession="false" name="Activity2" searchProperties="true" timeout="0">
      <con:settings/>
      <con:testStep type="datasource" name="DataSource" id="3e8729db-3c8c-4309-ba79-5bd7e95e1490">
        <con:settings/>
        <con:config xsi:type="con:DataSourceStep" xmlns:xsi="http://www.w3.org/2001/XMLSchema-instance">
          <con:dataSource type="Grid">
            <con:configuration>
              <check><![CDATA[<xml-fragment><con:entry xmlns:con="http://eviware.com/soapui/config">true</con:entry><con:entry xmlns:con="http://eviware.com/soapui/config">true</con:entry><con:entry xmlns:con="http://eviware.com/soapui/config">true</con:entry></xml-fragment>]]></check>
              <row><![CDATA[<xml-fragment><con:entry xmlns:con="http://eviware.com/soapui/config">77232</con:entry><con:entry xmlns:con="http://eviware.com/soapui/config">Riley</con:entry><con:entry xmlns:con="http://eviware.com/soapui/config">alive</con:entry><con:entry xmlns:con="http://eviware.com/soapui/config"/></xml-fragment>]]></row>
              <row><![CDATA[<xml-fragment><con:entry xmlns:con="http://eviware.com/soapui/config">77233</con:entry><con:entry xmlns:con="http://eviware.com/soapui/config">Gretel</con:entry><con:entry xmlns:con="http://eviware.com/soapui/config">alive</con:entry><con:entry xmlns:con="http://eviware.com/soapui/config"/></xml-fragment>]]></row>
              <row><![CDATA[<xml-fragment><con:entry xmlns:con="http://eviware.com/soapui/config">77234</con:entry><con:entry xmlns:con="http://eviware.com/soapui/config">Hansel</con:entry><con:entry xmlns:con="http://eviware.com/soapui/config">alive</con:entry><con:entry xmlns:con="http://eviware.com/soapui/config"/></xml-fragment>]]></row>
              <recognizeAsPlainText>true</recognizeAsPlainText>
            </con:configuration>
          </con:dataSource>
          <con:shared>true</con:shared>
          <con:restartShared>true</con:restartShared>
          <con:property>petId</con:property>
          <con:property>petName</con:property>
          <con:property>petStatus</con:property>
          <con:restartOnRun>true</con:restartOnRun>
          <con:stopDatasourceExhausted>false</con:stopDatasourceExhausted>
        </con:config>
      </con:testStep>
      <con:testStep type="restrequest" name="POST Request" id="ea0089fc-43b2-40b5-a5dc-6875182198ea">
        <con:settings/>
        <con:config service="https://petstore.swagger.io" resourcePath="/v2/pet" methodName="Pet" xsi:type="con:RestRequestStep" xmlns:xsi="http://www.w3.org/2001/XMLSchema-instance">
          <con:restRequest name="POST Request" id="43855870-2860-44c2-9d84-33fcd52848ef" mediaType="application/json" postQueryString="false">
            <con:settings>
              <con:setting id="com.eviware.soapui.impl.wsdl.WsdlRequest@request-headers">&lt;xml-fragment/></con:setting>
            </con:settings>
            <con:endpoint>https://petstore.swagger.io</con:endpoint>
            <con:request>{\r
   "id":${DataSource#petId},\r
   "name":"${DataSource#petName}",\r
   "status":"${DataSource#petStatus}"
}</con:request>
            <con:originalUri>https://petstore.swagger.io/v2/pet</con:originalUri>
            <con:assertion type="Valid HTTP Status Codes" id="1e037a9d-2b64-4b4c-9ccb-8edbe9ca662f" name="Valid HTTP Status Codes">
              <con:settings/>
              <con:configuration>
                <codes>200</codes>
              </con:configuration>
            </con:assertion>
            <con:assertion type="JsonPath Match" id="1dfbfa74-b9ff-4710-9b90-d594978be2ac" name="JSONPath Match">
              <con:configuration>
                <path>$['id']</path>
                <content>${POST Request#Response#$['id']}</content>
                <allowWildcards>false</allowWildcards>
                <ignoreNamspaceDifferences>false</ignoreNamspaceDifferences>
                <ignoreComments>false</ignoreComments>
              </con:configuration>
            </con:assertion>
            <con:credentials>
              <con:selectedAuthProfile>No Authorization</con:selectedAuthProfile>
              <con:authType>No Authorization</con:authType>
            </con:credentials>
            <con:jmsConfig JMSDeliveryMode="PERSISTENT"/>
            <con:parameters/>
          </con:restRequest>
        </con:config>
      </con:testStep>
      <con:testStep type="transfer" name="Property Transfer" id="9e7379d8-5411-4443-90d0-3e1eb54196f5">
        <con:settings/>
        <con:config xsi:type="con:PropertyTransfersStep" xmlns:xsi="http://www.w3.org/2001/XMLSchema-instance">
          <con:transfers setNullOnMissingSource="true" transferTextContent="true" failOnError="true" ignoreEmpty="false" transferToAll="false" entitize="false" transferChildNodes="false">
            <con:name>statusTransfer</con:name>
            <con:sourceType>Response</con:sourceType>
            <con:sourceStep>POST Request</con:sourceStep>
            <con:sourcePath>$['status']</con:sourcePath>
            <con:targetType>status</con:targetType>
            <con:targetStep>GET Request</con:targetStep>
            <con:targetPath/>
            <con:type>JSONPATH</con:type>
            <con:targetTransferType>JSONPATH</con:targetTransferType>
            <con:upgraded>true</con:upgraded>
          </con:transfers>
          <con:transfers setNullOnMissingSource="true" transferTextContent="true" failOnError="true" ignoreEmpty="false" transferToAll="false" entitize="false" transferChildNodes="false">
            <con:name>idTransfer</con:name>
            <con:sourceType>Response</con:sourceType>
            <con:sourceStep>POST Request</con:sourceStep>
            <con:sourcePath>$['id']</con:sourcePath>
            <con:targetType>petId</con:targetType>
            <con:targetStep>DELETE Request</con:targetStep>
            <con:type>JSONPATH</con:type>
            <con:targetTransferType>JSONPATH</con:targetTransferType>
            <con:upgraded>true</con:upgraded>
          </con:transfers>
        </con:config>
      </con:testStep>
      <con:testStep type="restrequest" name="GET Request" id="4bb4db13-b1cd-4842-b943-ac54b0cd01dc">
        <con:settings/>
        <con:config service="https://petstore.swagger.io" resourcePath="/v2/pet/findByStatus" methodName="FindByStatus" xsi:type="con:RestRequestStep" xmlns:xsi="http://www.w3.org/2001/XMLSchema-instance">
          <con:restRequest name="GET Request" id="42c9062d-c4e7-44d3-b3fa-de7cdee410bb" mediaType="application/json">
            <con:settings>
              <con:setting id="com.eviware.soapui.impl.wsdl.WsdlRequest@request-headers">&lt;xml-fragment/></con:setting>
            </con:settings>
            <con:endpoint>https://petstore.swagger.io</con:endpoint>
            <con:request/>
            <con:originalUri>https://petstore.swagger.io/v2/pet/findByStatus</con:originalUri>
            <con:assertion type="Valid HTTP Status Codes" id="ef97a2f6-551f-4064-99cc-ca49640d3484" name="Valid HTTP Status Codes">
              <con:settings/>
              <con:configuration>
                <codes>200</codes>
              </con:configuration>
            </con:assertion>
            <con:credentials>
              <con:selectedAuthProfile>No Authorization</con:selectedAuthProfile>
              <con:authType>No Authorization</con:authType>
            </con:credentials>
            <con:jmsConfig JMSDeliveryMode="PERSISTENT"/>
            <con:parameters>
              <con:entry key="status" value="alive"/>
            </con:parameters>
            <con:parameterOrder>
              <con:entry>status</con:entry>
            </con:parameterOrder>
          </con:restRequest>
        </con:config>
      </con:testStep>
      <con:testStep type="restrequest" name="DELETE Request" id="df8e2318-196c-40cc-af40-bcf1b46e22ef">
        <con:settings/>
        <con:config service="https://petstore.swagger.io" resourcePath="/v2/pet/{petId}" methodName="PetId" xsi:type="con:RestRequestStep" xmlns:xsi="http://www.w3.org/2001/XMLSchema-instance">
          <con:restRequest name="DELETE Request" id="d0086ff5-5e06-4bd9-8f9a-d324ddb62d6c" mediaType="application/json" postQueryString="false">
            <con:settings>
              <con:setting id="com.eviware.soapui.impl.wsdl.WsdlRequest@request-headers">&lt;xml-fragment/></con:setting>
            </con:settings>
            <con:endpoint>https://petstore.swagger.io</con:endpoint>
            <con:request/>
            <con:originalUri>https://petstore.swagger.io/v2/pet/77232</con:originalUri>
            <con:assertion type="Valid HTTP Status Codes" id="03572c51-d359-45b3-bb5a-e047330cbc4a" name="Valid HTTP Status Codes">
              <con:settings/>
              <con:configuration>
                <codes>200</codes>
              </con:configuration>
            </con:assertion>
            <con:credentials>
              <con:selectedAuthProfile>No Authorization</con:selectedAuthProfile>
              <con:authType>No Authorization</con:authType>
            </con:credentials>
            <con:jmsConfig JMSDeliveryMode="PERSISTENT"/>
            <con:parameters>
              <con:entry key="petId" value="77234"/>
            </con:parameters>
            <con:parameterOrder>
              <con:entry>petId</con:entry>
            </con:parameterOrder>
          </con:restRequest>
        </con:config>
      </con:testStep>
      <con:testStep type="datasourceloop" name="Data Source Loop" id="9c104f83-ede1-4f34-b672-e97b42f16755">
        <con:settings/>
        <con:config>
          <dataSourceStep>DataSource</dataSourceStep>
          <targetStep>POST Request</targetStep>
          <discardResults>true</discardResults>
        </con:config>
      </con:testStep>
      <con:properties/>
      <con:reportParameters/>
      <con:breakPoints>
        <con:testStepId>2169256e-c705-4913-9a43-486c4bbf487e</con:testStepId>
        <con:status>NONE</con:status>
        <con:properties/>
      </con:breakPoints>
      <con:breakPoints>
        <con:testStepId>9ab2a6eb-8f8f-4e5d-9093-c53673ebb812</con:testStepId>
        <con:status>NONE</con:status>
        <con:properties/>
      </con:breakPoints>
      <con:breakPoints>
        <con:testStepId>4714457b-d863-4720-8316-cdff75517eae</con:testStepId>
        <con:status>NONE</con:status>
        <con:properties/>
      </con:breakPoints>
      <con:breakPoints>
        <con:testStepId>308116ca-a6b5-46dd-bf3b-c75913794ab0</con:testStepId>
        <con:status>NONE</con:status>
        <con:properties/>
      </con:breakPoints>
      <con:breakPoints>
        <con:testStepId>3836a961-01fa-4237-9bf2-3592ab98d8bf</con:testStepId>
        <con:status>NONE</con:status>
        <con:properties/>
      </con:breakPoints>
      <con:breakPoints>
        <con:testStepId>bc022b69-9d68-433d-bb93-6340db648bf0</con:testStepId>
        <con:status>NONE</con:status>
        <con:properties/>
      </con:breakPoints>
    </con:testCase>
    <con:properties/>
    <con:reportParameters/>
  </con:testSuite>
  <con:requirements/>
  <con:properties/>
  <con:wssContainer/>
  <con:databaseConnectionContainer/>
  <con:jmsConnectionContainer/>
  <con:oAuth2ProfileContainer/>
  <con:oAuth1ProfileContainer/>
  <con:reporting>
    <con:xmlTemplates/>
    <con:parameters/>
  </con:reporting>
  <con:eventHandlers type="RequestFilter.filterRequest" name="RequestFilter.filterRequest">
    <con:script>// Sample event script to add custom HTTP header to all outgoing REST, SOAP and HTTP(S) calls
// This code is often used for adding custom authentication to ReadyAPI functional tests

// If hardcoding the token, uncomment and change line 5
// token = '4567'

// If your token is parameterized in Project level custom property, uncomment line 8
// token = request.parent.testCase.testSuite.project.getProperty('auth_token').getValue()

// To modify all outgoing calls, remove comments from lines 11 to 16
// headers = request.requestHeaders
// if (headers.containsKey('auth_token2') == false) {
//   headers.put('auth_token2', token)
//   request.requestHeaders = headers
// }</con:script>
  </con:eventHandlers>
  <con:eventHandlers type="TestRunListener.afterStep" name="TestRunListener.afterStep">
    <con:script>// Save all test step results into files
// Change the directory path in line 5 to a location where you want to store details
// then uncomment lines 5 to 10

// filePath = 'C:\\tempOutputDirectory\\'
// fos = new java.io.FileOutputStream(filePath + testStepResult.testStep.label + '.txt', true)
// pw = new java.io.PrintWriter(fos)
// testStepResult.writeTo(pw)
// pw.close()
// fos.close()</con:script>
  </con:eventHandlers>
  <con:authRepository/>
  <con:tags/>
</con:soapui-project>
